apppath/__init__.py
apppath/app_path.py
apppath/system_open_path_utilities.py
apppath/windows_path_utilities.py
apppath/entry_points/__init__.py
apppath/entry_points/clean_apppath.py
apppath/entry_points/open_apppath.py
Apppath-1.0.9.dist-info/LICENSE.md
Apppath-1.0.9.dist-info/METADATA
Apppath-1.0.9.dist-info/WHEEL
Apppath-1.0.9.dist-info/entry_points.txt
Apppath-1.0.9.dist-info/top_level.txt
Apppath-1.0.9.dist-info/RECORD
