Metadata-Version: 2.1
Name: Apppath
Version: 1.0.9
Summary: A package for easing return of multiple values
Home-page: https://github.com/pything/apppath
Download-URL: https://github.com/pything/apppath/releases
Author: Christian Heider Lindbjerg
Author-email: christian.heider@alexandra.dk
Maintainer: Christian Heider Lindbjerg
Maintainer-email: christian.heider@alexandra.dk
License: Apache License, Version 2.0
Keywords: app path paths data logs cache
Classifier: Development Status :: 4 - Beta
Classifier: Environment :: Console
Classifier: Intended Audience :: End Users/Desktop
Classifier: Intended Audience :: Developers
Classifier: License :: OSI Approved :: Apache Software License
Classifier: Operating System :: MacOS :: MacOS X
Classifier: Operating System :: Microsoft :: Windows
Classifier: Operating System :: POSIX
Classifier: Operating System :: OS Independent
Classifier: Programming Language :: Python :: 3
Classifier: Natural Language :: English
Requires-Python: >=3.6
License-File: LICENSE.md
Requires-Dist: warg>=1.4.8
Provides-Extra: all
Requires-Dist: warg>=1.4.8; extra == "all"
Requires-Dist: sphinxcontrib-programoutput; extra == "all"
Requires-Dist: apppath; extra == "all"
Requires-Dist: sphinx; extra == "all"
Requires-Dist: tqdm; extra == "all"
Requires-Dist: pytest-cov; extra == "all"
Requires-Dist: mock; extra == "all"
Requires-Dist: twine; extra == "all"
Requires-Dist: black; extra == "all"
Requires-Dist: pytest; extra == "all"
Requires-Dist: pip; extra == "all"
Requires-Dist: pytest-runner; extra == "all"
Requires-Dist: wheel; extra == "all"
Requires-Dist: coveralls; extra == "all"
Provides-Extra: dev
Requires-Dist: warg>=1.4.8; extra == "dev"
Requires-Dist: sphinxcontrib-programoutput; extra == "dev"
Requires-Dist: apppath; extra == "dev"
Requires-Dist: sphinx; extra == "dev"
Requires-Dist: pytest-cov; extra == "dev"
Requires-Dist: twine; extra == "dev"
Requires-Dist: black; extra == "dev"
Requires-Dist: pytest; extra == "dev"
Requires-Dist: pip; extra == "dev"
Requires-Dist: pytest-runner; extra == "dev"
Requires-Dist: wheel; extra == "dev"
Requires-Dist: coveralls; extra == "dev"
Provides-Extra: docs
Requires-Dist: apppath; extra == "docs"
Requires-Dist: sphinxcontrib-programoutput; extra == "docs"
Requires-Dist: sphinx; extra == "docs"
Provides-Extra: setup
Requires-Dist: tqdm; extra == "setup"
Requires-Dist: pytest-runner; extra == "setup"
Provides-Extra: tests
Requires-Dist: warg>=1.4.8; extra == "tests"
Requires-Dist: sphinxcontrib-programoutput; extra == "tests"
Requires-Dist: apppath; extra == "tests"
Requires-Dist: sphinx; extra == "tests"
Requires-Dist: pytest-cov; extra == "tests"
Requires-Dist: mock; extra == "tests"
Requires-Dist: twine; extra == "tests"
Requires-Dist: black; extra == "tests"
Requires-Dist: pytest; extra == "tests"
Requires-Dist: pip; extra == "tests"
Requires-Dist: pytest-runner; extra == "tests"
Requires-Dist: wheel; extra == "tests"
Requires-Dist: coveralls; extra == "tests"
